{
  "resumeHTML": "<div class=\"mb-4 p-4 border border-blue-100 rounded\">\n                            <p><strong>Aameer A Resume.docx</strong></p>\n                            <div class=\"flex flex-row gap-6 my-4\">\n                                <div class=\"flex flex-col items-center\">\n                                    <canvas id=\"donutMatch0\" width=\"100\" height=\"100\" style=\"display: block; box-sizing: border-box; height: 80px; width: 80px;\"></canvas>\n                                    <div class=\"mt-2 text-center text-xs font-semibold\">Match %</div>\n                                </div>\n                                <div class=\"flex flex-col items-center\">\n                                    <canvas id=\"donutSkills0\" width=\"103\" height=\"103\" style=\"display: block; box-sizing: border-box; height: 82px; width: 82px;\"></canvas>\n                                    <div class=\"mt-2 text-center text-xs font-semibold\">Skill Coverage</div>\n                                </div>\n                                <div class=\"flex flex-col items-center\">\n                                    <canvas id=\"donutExp0\" width=\"100\" height=\"100\" style=\"display: block; box-sizing: border-box; height: 80px; width: 80px;\"></canvas>\n                                    <div class=\"mt-2 text-center text-xs font-semibold\">Exp. Match</div>\n                                </div>\n                            </div>\n                            <p><strong>Resume Match:</strong> <span class=\"font-bold text-blue-600\">60%</span></p>\n                            <p><strong>Explanation:</strong> The candidate possesses many of the necessary .NET skills (ASP.NET, MVC, C#, Entity Framework, SQL Server) and demonstrates experience in web application development.  However, the resume shows only 3 years of experience, significantly less than the 4-7 years required.  Furthermore, the job description emphasizes experience with REST services and Azure, which are mentioned in the resume indirectly but lack specific demonstrable experience. The candidate's experience with Python and React, while valuable, isn't directly relevant to the core .NET requirements of this role. The use of Java is positive but not directly reflected in the project descriptions.</p>\n                        </div>",
  "audioHTML": "",
  "metaInfo": "",
  "timestamp": "6/28/2025, 1:28:39 AM",
  "technology": "",
  "audioFileName": ""
}